AUTHORS
CHANGES
LICENSE
MANIFEST.in
README
VERSION
ez_setup.py
setup.cfg
setup.py
tox.ini
comparison/Makefile
comparison/auto.mac
comparison/auto.rst
comparison/conf.py
comparison/index.rst
comparison/make.bat
comparison/starter.py
doc/Makefile
doc/aalength.mac
doc/aalength.rst
doc/authors.rst
doc/bpm.mac
doc/bpm.rst
doc/bugs.rst
doc/changes.rst
doc/conf.py
doc/conventions.rst
doc/downloads.rst
doc/example1.png
doc/example2.png
doc/example3.png
doc/examples.rst
doc/howto-build.rst
doc/howto-configure.rst
doc/howto-install.rst
doc/howto-markup.rst
doc/howto.rst
doc/in-source.png
doc/index.rst
doc/license.rst
doc/make.bat
doc/objectives.rst
doc/other.rst
doc/out-of-source1.png
doc/out-of-source2.png
doc/references.rst
doc/simple.mac
doc/simple.rst
doc/spec.rst
doc/starter.py
doc/style_guide.rst
doc/test1.png
doc/todo.rst
macros/ID12Bmetafile.mac
macros/attributes.mac
macros/ccdscan_4.0.mac
macros/cdef-examples.mac
macros/epics_mca_3.3.mac
macros/move.mac
macros/newuser.mac
macros/shutter.mac
macros/sphinx_shutter.mac
macros/test-battery.mac
macros/usaxs_load.mac
macros/usaxs_uascan.mac
markup_example/Makefile
markup_example/conf.py
markup_example/hkl_ioc.mac
markup_example/hkl_ioc.mac.original
markup_example/index.rst
markup_example/make.bat
markup_example/starter.py
sphinxcontrib/__init__.py
sphinxcontrib/specdomain.py
sphinxcontrib/specmacrofileparser.py
sphinxcontrib_specdomain.egg-info/PKG-INFO
sphinxcontrib_specdomain.egg-info/SOURCES.txt
sphinxcontrib_specdomain.egg-info/dependency_links.txt
sphinxcontrib_specdomain.egg-info/namespace_packages.txt
sphinxcontrib_specdomain.egg-info/not-zip-safe
sphinxcontrib_specdomain.egg-info/requires.txt
sphinxcontrib_specdomain.egg-info/top_level.txt
test/Makefile
test/ccdscan_4.0.mac.rst
test/cdef-examples.mac.rst
test/conf.py
test/index.rst
test/make.bat
test/python-example-source.rst
test/shutter.mac.rst
test/starter.py
test/test_autospecdir.rst
test/test_doc.rst
test/tester.py
test/tester2.py
test/tester3.py
test/tester4.py
test/tester5.py
test/tester6.py
test/tester7.py
test/usaxs_load.mac.rst
test/usaxs_uascan.mac.rst