Metadata-Version: 1.0
Name: sphinxcontrib-specdomain
Version: 1.04.02
Summary: Sphinx "specdomain" extension
Home-page: http://specdomain.readthedocs.org
Author: Pete Jemian
Author-email: jemian@anl.gov
License: Argonne OPEN SOURCE LICENSE, see LICENSE file for details
Platform: any
Classifier: Development Status :: 4 - Beta
Classifier: Environment :: Console
Classifier: Environment :: Web Environment
Classifier: Intended Audience :: Science/Research
Classifier: License :: Free To Use But Restricted
Classifier: Operating System :: OS Independent
Classifier: Programming Language :: Python
Classifier: Topic :: Documentation
Classifier: Topic :: Utilities
